codefinal_shared/__init__.py
codefinal_shared/auth.py
codefinal_shared/constants.py
codefinal_shared/models.py
codefinal_shared/serializers.py
codefinal_shared/validation.py
codefinal_shared_backend-1.0.0.dist-info/licenses/LICENSE
codefinal_shared_backend-1.0.0.dist-info/METADATA
codefinal_shared_backend-1.0.0.dist-info/WHEEL
codefinal_shared_backend-1.0.0.dist-info/top_level.txt
codefinal_shared_backend-1.0.0.dist-info/RECORD
