Metadata-Version: 2.4
Name: codefinal-shared-backend
Version: 1.0.0
Summary: Shared backend utilities for CodeFinal products
Home-page: https://github.com/CodeFinal/codefinal/tree/feature/COD-141-shared-component-library/packages/backend-utils
Author: CodeFinal Team
Author-email: team@codefinal.com
Project-URL: Bug Tracker, https://github.com/CodeFinal/codefinal/issues
Project-URL: Repository, https://github.com/CodeFinal/codefinal/tree/feature/COD-141-shared-component-library
Project-URL: Documentation, https://github.com/CodeFinal/codefinal/tree/feature/COD-141-shared-component-library/packages/backend-utils#readme
Keywords: django authentication shared utilities backend api
Classifier: Development Status :: 4 - Beta
Classifier: Intended Audience :: Developers
Classifier: License :: OSI Approved :: MIT License
Classifier: Programming Language :: Python :: 3
Classifier: Programming Language :: Python :: 3.8
Classifier: Programming Language :: Python :: 3.9
Classifier: Programming Language :: Python :: 3.10
Classifier: Programming Language :: Python :: 3.11
Classifier: Framework :: Django
Classifier: Environment :: Web Environment
Classifier: Operating System :: OS Independent
Classifier: Topic :: Internet :: WWW/HTTP
Classifier: Topic :: Internet :: WWW/HTTP :: Dynamic Content
Requires-Python: >=3.8
License-File: LICENSE
Requires-Dist: Django>=4.0.0
Requires-Dist: djangorestframework>=3.14.0
Requires-Dist: django-tenants>=3.0.0
Requires-Dist: pyotp>=2.6.0
Requires-Dist: python-decouple>=3.6
Requires-Dist: cryptography>=3.4.8
Provides-Extra: dev
Requires-Dist: pytest>=7.0.0; extra == "dev"
Requires-Dist: pytest-django>=4.0.0; extra == "dev"
Requires-Dist: black>=22.0.0; extra == "dev"
Requires-Dist: flake8>=4.0.0; extra == "dev"
Dynamic: author
Dynamic: author-email
Dynamic: classifier
Dynamic: description
Dynamic: description-content-type
Dynamic: home-page
Dynamic: keywords
Dynamic: license-file
Dynamic: project-url
Dynamic: provides-extra
Dynamic: requires-dist
Dynamic: requires-python
Dynamic: summary
